fasthtml_admin/__init__.py
fasthtml_admin/admin.py
fasthtml_admin/auth.py
fasthtml_admin/oauth.py
fasthtml_admin/utils.py
fasthtml_admin/validation.py
fasthtml_admin-0.1.2.dist-info/METADATA
fasthtml_admin-0.1.2.dist-info/WHEEL
fasthtml_admin-0.1.2.dist-info/licenses/LICENSE
fasthtml_admin-0.1.2.dist-info/RECORD
