Metadata-Version: 2.4
Name: fasthtml-admin
Version: 0.1.2
Summary: Providing helper user management and authentication functions for FastHTML
Project-URL: Homepage, https://github.com/AndreasThinks/fasthtml-admin
License-File: LICENSE
Requires-Python: >=3.12
Requires-Dist: bcrypt>=4.2.1
Requires-Dist: python-fasthtml>=0.12.1
